[
    {
        "title":"Вікторина про метали",
        "cover":"http://imdiv.com/images/quiz/ru/screens/38.jpg",
        "questions":
        [
          {
            "question":"Назвіть хімічний символ золота.",
            "true_reply":1,
            "answers":
            [
              "A","B","D"
            ]
          },
          {
            "question":"Правда чи брехня? Сталь є хімічним елементом.",
            "true_reply":1,
            "answers":
            [
              "Правда","Брехня"
            ]
          },
          {
            "question":"Назвіть найпоширеніший метал на Землі.",
            "true_reply":0,
            "answers":
            [
              "Залізо","Золото","Мідь"
            ]
          },
          {
            "question":"Правда чи брехня? Натрій дуже активний метал.",
            "true_reply":0,
            "answers":
            [
                "Правда","Брехня"
            ]
          },
          {
            "question":"Назвіть три види медалей, якими нагороджують переможців у Олімпійських Іграх.",
            "true_reply":0,
            "answers":
            [
                "Золота, срібна та бронзова","Залізо, срібна та бронзова"
            ]
          },
          {
            "question":"Правда чи брехня? З'єднання двох металів називається металевим зв'язком.",
            "true_reply":0,
            "answers":
            [
                "Правда","Брехня"
            ]
          }
        ]
    }
]